{
  "ShouldSerialize": false,
  "Address": "https://github.com/HOKGroup/HOK-Revit-Addins",
  "Frequency": "min1",
  "SourceAssets": [],
  "DestinationAssets": [
    {
      "LocationType": "Folder",
      "DirectoryPath": "C:\\ProgramData\\Autodesk\\Revit\\Addins\\2018\\HOK-Addin.bundle\\Contents",
      "Assets": [
        {
          "id": 8009907,
          "name": "EntityFramework.dll",
          "url": "https://api.github.com/repos/HOKGroup/HOK-Revit-Addins/releases/assets/8009907"
        },
        {
          "id": 8009908,
          "name": "EntityFramework.SqlServer.dll",
          "url": "https://api.github.com/repos/HOKGroup/HOK-Revit-Addins/releases/assets/8009908"
        }
      ]
    },
    {
      "LocationType": "Trash",
      "DirectoryPath": "C:\\ProgramData\\Autodesk\\Revit\\Addins\\2018\\HOK-Addin.bundle\\Contents",
      "Assets": [
        {
          "id": 8010054,
          "name": "HOK.Core.dll",
          "url": "https://api.github.com/repos/HOKGroup/HOK-Revit-Addins/releases/assets/8010054"
        },
        {
          "id": 8010055,
          "name": "HOK.MissionControl.Core.dll",
          "url": "https://api.github.com/repos/HOKGroup/HOK-Revit-Addins/releases/assets/8010055"
        }
      ]
    }
  ],
  "LatestRelease": {
    "id": 12105312,
    "tag_name": "0.0.0.5",
    "name": "0.0.0.5",
    "body": "This is my 3rd update!",
    "prerelease": true,
    "published_at": "2018-07-25T17:02:54-04:00",
    "author": {
      "login": "ksobon"
    },
    "assets": [
      {
        "id": 8009907,
        "name": "EntityFramework.dll",
        "url": "https://api.github.com/repos/HOKGroup/HOK-Revit-Addins/releases/assets/8009907"
      },
      {
        "id": 8009908,
        "name": "EntityFramework.SqlServer.dll",
        "url": "https://api.github.com/repos/HOKGroup/HOK-Revit-Addins/releases/assets/8009908"
      }
    ]
  }
}